{"bookmarks": {"charges": {"created": 1636989020}, "charges_events": {"updates_created": 1636984036}, "events": {"created": 1636989021}, "customers": {"created": 1636989021}, "customers_events": {"updates_created": 1636984036}, "invoices": {"date": 1636989022}, "invoice_line_items": {"date": 1636989022}, "invoices_events": {"updates_created": 1636984037}, "invoice_items": {"date": 1636989022}, "invoice_items_events": {"updates_created": 1636848000}, "transfers": {"created": 1636989023}, "transfers_events": {"updates_created": 1636984036}, "coupons": {"created": 1636989024}, "coupons_events": {"updates_created": 1636848000}, "subscriptions": {"created": 1636989024}, "subscription_items": {"created": 1636989024}, "subscriptions_events": {"updates_created": 1636980251}, "balance_transactions": {"created": 1636989025}, "payouts": {"created": 1636989025}, "payout_transactions": {"created": 1636989025}, "payouts_events": {"updates_created": 1636848000}, "disputes": {"created": 1636989025}, "disputes_events": {"updates_created": 1636848000}, "products": {"created": 1636989026}, "products_events": {"updates_created": 1636848000}}}
